{
  "region": "부산광역시",
  "regionSlug": "busan",
  "district": "사하구",
  "districtSlug": "saha",
  "updatedAt": "2026-03-27",
  "totalCount": 155,
  "stores": [
    {
      "name": "삼풍슈퍼",
      "address": "부산광역시 사하구 괴정동 487-7",
      "roadAddress": "부산광역시 사하구 사하로 157  (괴정동)",
      "status": "영업/정상",
      "licenseDate": ""
    },
    {
      "name": "JC마트",
      "address": "부산광역시 사하구 감천동 20-19",
      "roadAddress": "부산광역시 사하구 옥천로 36-1  (감천동)",
      "status": "영업/정상",
      "licenseDate": ""
    },
    {
      "name": "하프타임 신동양점",
      "address": "부산광역시 사하구 괴정동 773 신동양아파트 상가동 101호",
      "roadAddress": "",
      "status": "영업/정상",
      "licenseDate": ""
    },
    {
      "name": "삼성테스코 (주) 홈플러스 익스프레스 다대포점",
      "address": "부산광역시 사하구 다대동 1548-18",
      "roadAddress": "부산광역시 사하구 다대낙조2길 3  (다대동)",
      "status": "영업/정상",
      "licenseDate": ""
    },
    {
      "name": "세븐하단에덴점 (2816)",
      "address": "부산광역시 사하구 하단동 525-5",
      "roadAddress": "부산광역시 사하구 낙동남로1405번길 9-11  (하단동)",
      "status": "영업/정상",
      "licenseDate": ""
    },
    {
      "name": "gs25하단오복점",
      "address": "부산광역시 사하구 하단동 618-27",
      "roadAddress": "부산광역시 사하구 낙동대로 457  (하단동)",
      "status": "영업/정상",
      "licenseDate": ""
    },
    {
      "name": "훼미리마트당리하늘점",
      "address": "부산광역시 사하구 당리동 305-2",
      "roadAddress": "부산광역시 사하구 낙동대로450번길 12  (당리동)",
      "status": "영업/정상",
      "licenseDate": ""
    },
    {
      "name": "창신마트",
      "address": "부산광역시 사하구 당리동 237-2 창신아파트 상가동 102호",
      "roadAddress": "부산광역시 사하구 승학로17번길 20, 상가동 102호 (당리동,창신아파트)",
      "status": "영업/정상",
      "licenseDate": ""
    },
    {
      "name": "만복래미니마트",
      "address": "부산광역시 사하구 괴정동 488-4 신동화상가동 101호",
      "roadAddress": "부산광역시 사하구 괴정로270번길 29, 신동화상가동 101호 (괴정동)",
      "status": "영업/정상",
      "licenseDate": ""
    },
    {
      "name": "천냥 D. C마트",
      "address": "부산광역시 사하구 감천동 541-1",
      "roadAddress": "부산광역시 사하구 옥천로 20  (감천동)",
      "status": "영업/정상",
      "licenseDate": ""
    },
    {
      "name": "유성슈퍼",
      "address": "부산광역시 사하구 장림동 671-10",
      "roadAddress": "부산광역시 사하구 장림로 181  (장림동)",
      "status": "영업/정상",
      "licenseDate": "2009-03-09"
    },
    {
      "name": "C마트",
      "address": "부산광역시 사하구 괴정동 1050",
      "roadAddress": "부산광역시 사하구 승학로 233  (괴정동)",
      "status": "영업/정상",
      "licenseDate": "2009-03-19"
    },
    {
      "name": "부산할인마트",
      "address": "부산광역시 사하구 감천동 53-25",
      "roadAddress": "부산광역시 사하구 감천로 173-1  (감천동)",
      "status": "영업/정상",
      "licenseDate": "2009-03-24"
    },
    {
      "name": "행복한마트(GS25 괴정글샘점)",
      "address": "부산광역시 사하구 괴정동 885-2",
      "roadAddress": "부산광역시 사하구 낙동대로233번길 19  (괴정동)",
      "status": "영업/정상",
      "licenseDate": "2009-04-07"
    },
    {
      "name": "L마트",
      "address": "부산광역시 사하구 다대동 120-10 삼환아파트 1동 지하호",
      "roadAddress": "",
      "status": "영업/정상",
      "licenseDate": "2009-04-22"
    },
    {
      "name": "하나슈퍼",
      "address": "부산광역시 사하구 다대동 113-15 도개공상가 가동 101호",
      "roadAddress": "부산광역시 사하구 다대로 474, 가동 101호 (다대동,도개공상가)",
      "status": "영업/정상",
      "licenseDate": "2009-04-21"
    },
    {
      "name": "삼성테스코(주)홈플러스 익스프레스 다대포점",
      "address": "부산광역시 사하구 다대동 1548-18",
      "roadAddress": "부산광역시 사하구 다대낙조2길 3  (다대동)",
      "status": "영업/정상",
      "licenseDate": "2009-04-27"
    },
    {
      "name": "삼성테스코(주) 홈플러스 익스프레스 부산하단점",
      "address": "부산광역시 사하구 하단동 1184-1 1184-2,1184-3 강변프라자빌라 101",
      "roadAddress": "부산광역시 사하구 하신번영로201번길 10  (하단동,1184-2,1184-3 강변프라자빌라 101)",
      "status": "영업/정상",
      "licenseDate": "2009-04-27"
    },
    {
      "name": "GS25하단동매점",
      "address": "부산광역시 사하구 하단동 608-1",
      "roadAddress": "부산광역시 사하구 하신중앙로 296  (하단동)",
      "status": "영업/정상",
      "licenseDate": "2009-04-29"
    },
    {
      "name": "롯데쇼핑(주)롯데슈퍼장림점",
      "address": "부산광역시 사하구 장림동 287-1",
      "roadAddress": "부산광역시 사하구 다대로277번길 12  (장림동)",
      "status": "영업/정상",
      "licenseDate": "2009-05-04"
    },
    {
      "name": "신다대할인마트",
      "address": "부산광역시 사하구 다대동 113-5 다대3지구도개공아파트상가 라동 101호",
      "roadAddress": "부산광역시 사하구 다대로 394, 라동 101호 (다대동,다대3지구도개공아파트상가)",
      "status": "영업/정상",
      "licenseDate": "2009-05-14"
    },
    {
      "name": "후레쉬원편의점",
      "address": "부산광역시 사하구 신평동 430-30",
      "roadAddress": "부산광역시 사하구 비봉로 38  (신평동)",
      "status": "영업/정상",
      "licenseDate": "2009-05-15"
    },
    {
      "name": "롯데쇼핑(주)롯데슈퍼당리점",
      "address": "부산광역시 사하구 당리동 115",
      "roadAddress": "부산광역시 사하구 제석로 68  (당리동)",
      "status": "영업/정상",
      "licenseDate": "2009-05-25"
    },
    {
      "name": "태양잡화슈퍼",
      "address": "부산광역시 사하구 다대동 943-14",
      "roadAddress": "부산광역시 사하구 윤공단로 12  (다대동)",
      "status": "영업/정상",
      "licenseDate": "2009-06-02"
    },
    {
      "name": "플러스마트",
      "address": "부산광역시 사하구 괴정동 1093-8",
      "roadAddress": "부산광역시 사하구 낙동대로302번길 33  (괴정동)",
      "status": "영업/정상",
      "licenseDate": "2009-06-03"
    },
    {
      "name": "서부산농업협동조합",
      "address": "부산광역시 사하구 당리동 317-45",
      "roadAddress": "부산광역시 사하구 낙동대로 394 (당리동)",
      "status": "영업/정상",
      "licenseDate": "2009-06-04"
    },
    {
      "name": "훼미리마트당리하늘점",
      "address": "부산광역시 사하구 당리동 305-2 1층",
      "roadAddress": "부산광역시 사하구 낙동대로450번길 12  (당리동,1층)",
      "status": "영업/정상",
      "licenseDate": "2009-06-04"
    },
    {
      "name": "정우마트당리점",
      "address": "부산광역시 사하구 당리동 431",
      "roadAddress": "부산광역시 사하구 마하로5번길 7  (당리동)",
      "status": "영업/정상",
      "licenseDate": "2009-06-09"
    },
    {
      "name": "포시즌슈퍼",
      "address": "부산광역시 사하구 하단동 487-1 청록미르피아 301동 101호",
      "roadAddress": "부산광역시 사하구 낙동대로549번길 29, 301동 101호 (하단동,청록미르피아)",
      "status": "영업/정상",
      "licenseDate": "2009-06-17"
    },
    {
      "name": "정우마트하단점24시",
      "address": "부산광역시 사하구 하단동 525-2",
      "roadAddress": "부산광역시 사하구 낙동남로 1389  (하단동)",
      "status": "영업/정상",
      "licenseDate": "2009-06-29"
    },
    {
      "name": "훼미리마트 동아대2호점",
      "address": "부산광역시 사하구 하단동 872-13 1층",
      "roadAddress": "부산광역시 사하구 낙동대로550번길 13  (하단동,1층)",
      "status": "영업/정상",
      "licenseDate": "2009-06-30"
    },
    {
      "name": "준호마트",
      "address": "부산광역시 사하구 당리동 325-2 리치하우스제지하층 106,107,108,109호",
      "roadAddress": "부산광역시 사하구 낙동대로 407-1  (당리동,리치하우스제지하층 106,107,108,109호)",
      "status": "영업/정상",
      "licenseDate": "2009-07-07"
    },
    {
      "name": "논스톱사하점",
      "address": "부산광역시 사하구 당리동 316-27",
      "roadAddress": "부산광역시 사하구 낙동대로 410  (당리동)",
      "status": "영업/정상",
      "licenseDate": "2009-07-08"
    },
    {
      "name": "인덕건재탑마트",
      "address": "부산광역시 사하구 하단동 592-7",
      "roadAddress": "부산광역시 사하구 낙동남로 1400  (하단동)",
      "status": "영업/정상",
      "licenseDate": "2009-07-22"
    },
    {
      "name": "(주)서원유통 탑마트감천점",
      "address": "부산광역시 사하구 감천동 577",
      "roadAddress": "부산광역시 사하구 감천로 29 (감천동)",
      "status": "영업/정상",
      "licenseDate": "2009-08-07"
    },
    {
      "name": "빅세일마트괴정점",
      "address": "부산광역시 사하구 괴정동 235 6통7반",
      "roadAddress": "부산광역시 사하구 대티로1번길 39  (괴정동)",
      "status": "영업/정상",
      "licenseDate": "2009-08-21"
    },
    {
      "name": "바이킹괴정점",
      "address": "부산광역시 사하구 괴정동 1238-293",
      "roadAddress": "부산광역시 사하구 낙동대로 155  (괴정동)",
      "status": "영업/정상",
      "licenseDate": "2009-09-01"
    },
    {
      "name": "럭키슈퍼렛",
      "address": "부산광역시 사하구 감천동 315-2",
      "roadAddress": "부산광역시 사하구 암남공원로 527  (감천동)",
      "status": "영업/정상",
      "licenseDate": "2009-09-02"
    },
    {
      "name": "백억할인마트",
      "address": "부산광역시 사하구 신평동 161-134",
      "roadAddress": "부산광역시 사하구 다대로142번길 133  (신평동)",
      "status": "영업/정상",
      "licenseDate": "2009-09-03"
    },
    {
      "name": "세븐일레븐 부산하단 미래점",
      "address": "부산광역시 사하구 하단동 596-14",
      "roadAddress": "부산광역시 사하구 낙동남로 1388  (하단동)",
      "status": "영업/정상",
      "licenseDate": "2009-09-14"
    },
    {
      "name": "(주) 지에스리테일 다대점",
      "address": "부산광역시 사하구 다대동 1624 외7필지롯데캐슬주상가지하101~110호",
      "roadAddress": "부산광역시 사하구 다대낙조2길 100  (다대동,외7필지롯데캐슬주상가지하101~110호)",
      "status": "영업/정상",
      "licenseDate": "2009-09-11"
    },
    {
      "name": "훼미리마트하단에덴점",
      "address": "부산광역시 사하구 하단동 518-16",
      "roadAddress": "부산광역시 사하구 하신번영로300번길 77  (하단동)",
      "status": "영업/정상",
      "licenseDate": "2009-09-14"
    },
    {
      "name": "미광슈퍼",
      "address": "부산광역시 사하구 감천동 13-1113",
      "roadAddress": "",
      "status": "영업/정상",
      "licenseDate": "2009-09-22"
    },
    {
      "name": "세일마트",
      "address": "부산광역시 사하구 괴정동 352-34",
      "roadAddress": "부산광역시 사하구 오작로 104  (괴정동)",
      "status": "영업/정상",
      "licenseDate": "2009-09-30"
    },
    {
      "name": "LOVE BEAR 24시편의점 장림점",
      "address": "부산광역시 사하구 장림동 333-2",
      "roadAddress": "부산광역시 사하구 장림번영로 50  (장림동)",
      "status": "영업/정상",
      "licenseDate": ""
    },
    {
      "name": "GS25사하신평점",
      "address": "부산광역시 사하구 신평동 165-3",
      "roadAddress": "부산광역시 사하구 장평로 303  (신평동)",
      "status": "영업/정상",
      "licenseDate": ""
    },
    {
      "name": "현대할인마트",
      "address": "부산광역시 사하구 괴정동 342-3 현대신델라맨션 상가1층동 6호",
      "roadAddress": "부산광역시 사하구 낙동대로 106, 상가1층동 6호 (괴정동,현대신델라맨션)",
      "status": "영업/정상",
      "licenseDate": "2009-11-05"
    },
    {
      "name": "포시즌괴정3호점",
      "address": "부산광역시 사하구 괴정동 553-9 1층동",
      "roadAddress": "부산광역시 사하구 장평로 441, 1층동 (괴정동)",
      "status": "영업/정상",
      "licenseDate": "2009-11-10"
    },
    {
      "name": "ing25(괴정점)",
      "address": "부산광역시 사하구 괴정동 487-7 삼풍@상가",
      "roadAddress": "부산광역시 사하구 사하로 157  (괴정동,삼풍@상가)",
      "status": "영업/정상",
      "licenseDate": "2009-11-16"
    },
    {
      "name": "훼미리마트 구평점",
      "address": "부산광역시 사하구 구평동 125-16",
      "roadAddress": "부산광역시 사하구 을숙도대로 746  (구평동)",
      "status": "영업/정상",
      "licenseDate": "2009-11-20"
    },
    {
      "name": "서일마트",
      "address": "부산광역시 사하구 감천동 363-8",
      "roadAddress": "부산광역시 사하구 암남공원로521번길 23  (감천동)",
      "status": "영업/정상",
      "licenseDate": "2009-11-24"
    },
    {
      "name": "홈마트",
      "address": "부산광역시 사하구 다대동 93-8 보광빌딩2층 201호",
      "roadAddress": "부산광역시 사하구 다대로381번길 46,  201호 (다대동,보광빌딩2층)",
      "status": "영업/정상",
      "licenseDate": "2009-11-30"
    },
    {
      "name": "탑플러스마트",
      "address": "부산광역시 사하구 괴정동 428-1",
      "roadAddress": "부산광역시 사하구 낙동대로189번길 1  (괴정동)",
      "status": "영업/정상",
      "licenseDate": "2009-12-02"
    },
    {
      "name": "하프타임신동양점",
      "address": "부산광역시 사하구 괴정동 733 신동양아파트 상가동 101,102호",
      "roadAddress": "부산광역시 사하구 낙동대로 265, 상가동 101,102호 (괴정동,신동양아파트)",
      "status": "영업/정상",
      "licenseDate": "2009-12-03"
    },
    {
      "name": "1번가생식마트",
      "address": "부산광역시 사하구 신평동 111-215",
      "roadAddress": "부산광역시 사하구 다대로130번길 59  (신평동)",
      "status": "영업/정상",
      "licenseDate": "2009-12-03"
    },
    {
      "name": "럭키슈퍼가락타운점",
      "address": "부산광역시 사하구 하단동 1175 가락타운2단지아파트 227동 108~9호",
      "roadAddress": "",
      "status": "영업/정상",
      "licenseDate": "2009-12-07"
    },
    {
      "name": "정마트",
      "address": "부산광역시 사하구 하단동 885-7",
      "roadAddress": "부산광역시 사하구 하신번영로 314  (하단동)",
      "status": "영업/정상",
      "licenseDate": "2009-12-15"
    },
    {
      "name": "미진마트 장림점",
      "address": "부산광역시 사하구 장림동 328-25",
      "roadAddress": "부산광역시 사하구 장림번영로 19  (장림동)",
      "status": "영업/정상",
      "licenseDate": "2009-12-28"
    },
    {
      "name": "훼미리마트 괴정점",
      "address": "부산광역시 사하구 괴정동 486-1",
      "roadAddress": "",
      "status": "영업/정상",
      "licenseDate": "2010-01-04"
    },
    {
      "name": "나래할인마트",
      "address": "부산광역시 사하구 신평동 84-97",
      "roadAddress": "부산광역시 사하구 신산로 197  (신평동)",
      "status": "영업/정상",
      "licenseDate": "2010-01-07"
    },
    {
      "name": "훼미리마트하단복개로점",
      "address": "부산광역시 사하구 하단동 625-11",
      "roadAddress": "부산광역시 사하구 괴정로 83  (하단동)",
      "status": "영업/정상",
      "licenseDate": "2010-01-28"
    },
    {
      "name": "하프타임진성점",
      "address": "부산광역시 사하구 하단동 526-17",
      "roadAddress": "부산광역시 사하구 낙동남로 1419  (하단동)",
      "status": "영업/정상",
      "licenseDate": "2010-02-10"
    },
    {
      "name": "폴마트",
      "address": "부산광역시 사하구 신평동 597-7",
      "roadAddress": "부산광역시 사하구 하신번영로173번길 20  (신평동)",
      "status": "영업/정상",
      "licenseDate": "2010-02-18"
    },
    {
      "name": "대가고기백화점",
      "address": "부산광역시 사하구 하단동 1180-11",
      "roadAddress": "부산광역시 사하구 하신번영로 207  (하단동)",
      "status": "영업/정상",
      "licenseDate": "2010-02-22"
    },
    {
      "name": "연화슈퍼",
      "address": "부산광역시 사하구 구평동 435-14",
      "roadAddress": "",
      "status": "영업/정상",
      "licenseDate": "2010-02-22"
    },
    {
      "name": "신미화당버들슈퍼",
      "address": "부산광역시 사하구 신평동 82-24",
      "roadAddress": "",
      "status": "영업/정상",
      "licenseDate": "2010-03-22"
    },
    {
      "name": "포시즌",
      "address": "부산광역시 사하구 괴정동 896-1",
      "roadAddress": "부산광역시 사하구 낙동대로 248  (괴정동)",
      "status": "영업/정상",
      "licenseDate": "2010-03-24"
    },
    {
      "name": "을숙도문화매점",
      "address": "부산광역시 사하구 하단동 1151-14",
      "roadAddress": "부산광역시 사하구 낙동남로1233번길 25  (하단동)",
      "status": "영업/정상",
      "licenseDate": "2010-03-24"
    },
    {
      "name": "GS25당리문화점",
      "address": "부산광역시 사하구 당리동 321-1 경성리치W아파트 B동 103호",
      "roadAddress": "부산광역시 사하구 낙동대로 388, B동 103호 (당리동,경성리치W아파트)",
      "status": "영업/정상",
      "licenseDate": "2010-03-26"
    },
    {
      "name": "GS25구평공단점",
      "address": "부산광역시 사하구 구평동 476-7",
      "roadAddress": "부산광역시 사하구 감천항로 433  (구평동)",
      "status": "영업/정상",
      "licenseDate": "2010-03-30"
    },
    {
      "name": "GS25괴정뉴코아점",
      "address": "부산광역시 사하구 괴정동 969-5",
      "roadAddress": "부산광역시 사하구 사하로 199-1  (괴정동)",
      "status": "영업/정상",
      "licenseDate": "2010-03-30"
    },
    {
      "name": "훼미리마트 감천유림점",
      "address": "부산광역시 사하구 감천동 808 유림아파트 상가동 B-101호",
      "roadAddress": "부산광역시 사하구 감천로 24, 상가동 B-101호 (감천동,유림아파트)",
      "status": "영업/정상",
      "licenseDate": "2010-04-06"
    },
    {
      "name": "킹마트",
      "address": "부산광역시 사하구 괴정동 1078-1 성림상가 1층",
      "roadAddress": "부산광역시 사하구 마하로 36  (괴정동,성림상가 1층)",
      "status": "영업/정상",
      "licenseDate": "2010-04-09"
    },
    {
      "name": "ing25",
      "address": "부산광역시 사하구 괴정동 487-6 삼풍아파트상가",
      "roadAddress": "부산광역시 사하구 사하로 157  (괴정동,삼풍아파트상가)",
      "status": "영업/정상",
      "licenseDate": "2010-04-14"
    },
    {
      "name": "썬마트",
      "address": "부산광역시 사하구 신평동 33-98",
      "roadAddress": "부산광역시 사하구 다대로 127-12  (신평동)",
      "status": "영업/정상",
      "licenseDate": "2010-04-21"
    },
    {
      "name": "하프타임",
      "address": "부산광역시 사하구 장림동 1118-7",
      "roadAddress": "부산광역시 사하구 장림로 159  (장림동)",
      "status": "영업/정상",
      "licenseDate": "2010-04-27"
    },
    {
      "name": "청운슈퍼",
      "address": "부산광역시 사하구 하단동 514-1",
      "roadAddress": "부산광역시 사하구 낙동남로1405번길 31  (하단동)",
      "status": "영업/정상",
      "licenseDate": "2010-05-04"
    },
    {
      "name": "신익마트",
      "address": "부산광역시 사하구 신평동 408 신익강변1차아파트 상가동 101호",
      "roadAddress": "부산광역시 사하구 하신중앙로 180, 상가동 101호 (신평동,신익강변1차아파트)",
      "status": "영업/정상",
      "licenseDate": "2010-05-04"
    },
    {
      "name": "GS25하단본동점",
      "address": "부산광역시 사하구 하단동 617-17",
      "roadAddress": "부산광역시 사하구 낙동대로457번길 22  (하단동)",
      "status": "영업/정상",
      "licenseDate": "2010-05-10"
    },
    {
      "name": "미화당만석군슈퍼마켓",
      "address": "부산광역시 사하구 감천동 648-7",
      "roadAddress": "부산광역시 사하구 감천로43번길 10  (감천동)",
      "status": "영업/정상",
      "licenseDate": "2010-05-14"
    },
    {
      "name": "하프타임동아대점",
      "address": "부산광역시 사하구 하단동 490-7",
      "roadAddress": "부산광역시 사하구 낙동대로 543  (하단동)",
      "status": "영업/정상",
      "licenseDate": "2010-05-25"
    },
    {
      "name": "탑플러스마트",
      "address": "부산광역시 사하구 하단동 492-2 대우에덴프라자 지하1층 110호",
      "roadAddress": "부산광역시 사하구 낙동대로 542,  110호 (하단동,대우에덴프라자 지하1층)",
      "status": "영업/정상",
      "licenseDate": "2010-05-26"
    },
    {
      "name": "미니스톱하단길은점",
      "address": "부산광역시 사하구 하단동 514-16",
      "roadAddress": "부산광역시 사하구 낙동남로1405번길 9  (하단동)",
      "status": "영업/정상",
      "licenseDate": "2010-05-26"
    },
    {
      "name": "GS25하단강변점",
      "address": "부산광역시 사하구 하단동 1157-12",
      "roadAddress": "부산광역시 사하구 하신번영로 405  (하단동)",
      "status": "영업/정상",
      "licenseDate": "2010-05-28"
    },
    {
      "name": "GS25동아대점",
      "address": "부산광역시 사하구 하단동 494-1 캠퍼스프라자103~104호",
      "roadAddress": "부산광역시 사하구 낙동대로516번길 56  (하단동,캠퍼스프라자103~104호)",
      "status": "영업/정상",
      "licenseDate": "2010-06-10"
    },
    {
      "name": "럭키슈퍼렛",
      "address": "부산광역시 사하구 감천동 315-2 남성타워아파트 1동 101호",
      "roadAddress": "부산광역시 사하구 암남공원로 527, 1동 101호 (감천동,남성타워아파트)",
      "status": "영업/정상",
      "licenseDate": "2010-06-16"
    },
    {
      "name": "서원탑훼미리마트",
      "address": "부산광역시 사하구 하단동 125-3",
      "roadAddress": "부산광역시 사하구 낙동대로451번길 34  (하단동)",
      "status": "영업/정상",
      "licenseDate": "2010-06-18"
    },
    {
      "name": "부산슈퍼",
      "address": "부산광역시 사하구 감천동 502-21",
      "roadAddress": "부산광역시 사하구 감천로89번길 15  (감천동)",
      "status": "영업/정상",
      "licenseDate": "2010-06-30"
    },
    {
      "name": "훼미리마트하단골드점",
      "address": "부산광역시 사하구 하단동 526-1",
      "roadAddress": "부산광역시 사하구 낙동남로1405번길 6  (하단동)",
      "status": "영업/정상",
      "licenseDate": "2010-07-05"
    },
    {
      "name": "다대참마트",
      "address": "부산광역시 사하구 다대동 113-12 도시개발공사3지구아파트 상가 나동 지하1호",
      "roadAddress": "부산광역시 사하구 다대로 440, 상가 나동 지하1호 (다대동,도시개발공사3지구아파트)",
      "status": "영업/정상",
      "licenseDate": "2010-07-07"
    },
    {
      "name": "훼미리마트하단모아점",
      "address": "부산광역시 사하구 하단동 489-7",
      "roadAddress": "부산광역시 사하구 낙동대로535번길 18  (하단동)",
      "status": "영업/정상",
      "licenseDate": "2010-07-19"
    },
    {
      "name": "한일슈퍼퍼",
      "address": "부산광역시 사하구 감천동 13-993",
      "roadAddress": "부산광역시 사하구 옥천로 62-2  (감천동)",
      "status": "영업/정상",
      "licenseDate": "2010-07-20"
    },
    {
      "name": "세븐일레븐부산하단가락점",
      "address": "부산광역시 사하구 하단동 885-9",
      "roadAddress": "부산광역시 사하구 하신번영로 312  (하단동)",
      "status": "영업/정상",
      "licenseDate": "2010-07-22"
    },
    {
      "name": "훼미리마트장림파워점",
      "address": "부산광역시 사하구 장림동 45-1",
      "roadAddress": "부산광역시 사하구 다대로277번길 23  (장림동)",
      "status": "영업/정상",
      "licenseDate": "2010-07-23"
    },
    {
      "name": "GS25 다대비치점",
      "address": "부산광역시 사하구 다대동 1552-11",
      "roadAddress": "부산광역시 사하구 다대로 680  (다대동)",
      "status": "영업/정상",
      "licenseDate": "2010-07-28"
    },
    {
      "name": "훼미리마트 다대플러스점",
      "address": "부산광역시 사하구 다대동 1577-1",
      "roadAddress": "",
      "status": "영업/정상",
      "licenseDate": "2010-07-29"
    },
    {
      "name": "C&I 24",
      "address": "부산광역시 사하구 감천동 468-11",
      "roadAddress": "부산광역시 사하구 옥천로 3  (감천동)",
      "status": "영업/정상",
      "licenseDate": "2010-08-02"
    },
    {
      "name": "다인할인마트",
      "address": "부산광역시 사하구 하단동 503-46",
      "roadAddress": "부산광역시 사하구 하신번영로328번길 25  (하단동)",
      "status": "영업/정상",
      "licenseDate": "2010-08-12"
    },
    {
      "name": "후레쉬원",
      "address": "부산광역시 사하구 하단동 487-1 301동 101호",
      "roadAddress": "부산광역시 사하구 낙동대로549번길 29, 301동 101호 (하단동)",
      "status": "영업/정상",
      "licenseDate": "2010-08-17"
    },
    {
      "name": "럭키무지개마트",
      "address": "부산광역시 사하구 신평동 206-5 럭키무지개아파트 상가동 2층호",
      "roadAddress": "",
      "status": "영업/정상",
      "licenseDate": "2010-08-23"
    },
    {
      "name": "국제마트",
      "address": "부산광역시 사하구 다대동 94-2",
      "roadAddress": "부산광역시 사하구 다대로381번길 75  (다대동)",
      "status": "영업/정상",
      "licenseDate": "2010-09-02"
    },
    {
      "name": "동양마트",
      "address": "부산광역시 사하구 신평동 428",
      "roadAddress": "부산광역시 사하구 비봉로 46  (신평동)",
      "status": "영업/정상",
      "licenseDate": "2010-09-03"
    },
    {
      "name": "훼미리마트 당리해별점",
      "address": "부산광역시 사하구 당리동 313-33",
      "roadAddress": "부산광역시 사하구 승학로 54  (당리동)",
      "status": "영업/정상",
      "licenseDate": "2010-09-08"
    },
    {
      "name": "신다대할인마트",
      "address": "부산광역시 사하구 다대동 113-5 도시개발공사3지구아파트 상가동 라-101호",
      "roadAddress": "부산광역시 사하구 다대로 394, 상가동 라-101호 (다대동,도시개발공사3지구아파트)",
      "status": "영업/정상",
      "licenseDate": "2010-09-15"
    },
    {
      "name": "GS25사하구평점",
      "address": "부산광역시 사하구 구평동 217",
      "roadAddress": "부산광역시 사하구 감천항로 187  (구평동)",
      "status": "영업/정상",
      "licenseDate": "2010-09-16"
    },
    {
      "name": "화성슈퍼",
      "address": "부산광역시 사하구 구평동 435-215 2통2반",
      "roadAddress": "",
      "status": "영업/정상",
      "licenseDate": "2010-09-17"
    },
    {
      "name": "메가박스",
      "address": "부산광역시 사하구 하단동 889-1",
      "roadAddress": "",
      "status": "영업/정상",
      "licenseDate": "2010-09-28"
    },
    {
      "name": "세븐일레븐 부산다대롯데캐슬점",
      "address": "부산광역시 사하구 다대동 1624 다대롯데캐슬몰운대아파트 상가동 104호",
      "roadAddress": "부산광역시 사하구 다대낙조2길 100, 상가동 104호 (다대동,다대롯데캐슬몰운대아파트)",
      "status": "영업/정상",
      "licenseDate": "2010-09-30"
    },
    {
      "name": "감천지업사",
      "address": "부산광역시 사하구 감천동 471",
      "roadAddress": "부산광역시 사하구 옥천로 8  (감천동)",
      "status": "영업/정상",
      "licenseDate": "2010-09-30"
    },
    {
      "name": "삼성공인중개사",
      "address": "부산광역시 사하구 구평동 106",
      "roadAddress": "부산광역시 사하구 을숙도대로 741  (구평동)",
      "status": "영업/정상",
      "licenseDate": "2010-10-04"
    },
    {
      "name": "지에스25하단종로점",
      "address": "부산광역시 사하구 하단동 616-8 보해이브빌 101호",
      "roadAddress": "부산광역시 사하구 하신중앙로 324,  101호 (하단동,보해이브빌)",
      "status": "영업/정상",
      "licenseDate": "2010-10-11"
    },
    {
      "name": "훼미리마트 신평역점",
      "address": "부산광역시 사하구 신평동 452-23",
      "roadAddress": "부산광역시 사하구 하신중앙로 176  (신평동)",
      "status": "영업/정상",
      "licenseDate": "2010-10-15"
    },
    {
      "name": "비디오까페당리점",
      "address": "부산광역시 사하구 당리동 313-4",
      "roadAddress": "부산광역시 사하구 승학로 52  (당리동)",
      "status": "영업/정상",
      "licenseDate": "2010-10-19"
    },
    {
      "name": "탑플러스마트",
      "address": "부산광역시 사하구 괴정동 764-90",
      "roadAddress": "부산광역시 사하구 승학로 190  (괴정동)",
      "status": "영업/정상",
      "licenseDate": "2010-10-25"
    },
    {
      "name": "정원문구",
      "address": "부산광역시 사하구 괴정동 586-58",
      "roadAddress": "부산광역시 사하구 괴정로 177  (괴정동)",
      "status": "영업/정상",
      "licenseDate": "2010-11-10"
    },
    {
      "name": "협신킹마트",
      "address": "부산광역시 사하구 괴정동 197-1 초원빌 101호",
      "roadAddress": "부산광역시 사하구 대티로 45,  101호 (괴정동,초원빌)",
      "status": "영업/정상",
      "licenseDate": "2010-11-11"
    },
    {
      "name": "킹할인마트",
      "address": "부산광역시 사하구 하단동 500-43",
      "roadAddress": "부산광역시 사하구 낙동대로535번길 25  (하단동)",
      "status": "영업/정상",
      "licenseDate": "2010-11-30"
    },
    {
      "name": "훼미리마트다대현대점",
      "address": "부산광역시 사하구 다대동 308-2 일영빌딩 A-201",
      "roadAddress": "부산광역시 사하구 다대로 485  (다대동,일영빌딩 A-201)",
      "status": "영업/정상",
      "licenseDate": "2010-12-07"
    },
    {
      "name": "GS25다대희망점",
      "address": "부산광역시 사하구 다대동 647-6",
      "roadAddress": "부산광역시 사하구 다대로 584  (다대동)",
      "status": "영업/정상",
      "licenseDate": "2010-12-17"
    },
    {
      "name": "ING편의점",
      "address": "부산광역시 사하구 당리동 313-34",
      "roadAddress": "부산광역시 사하구 낙동대로 434  (당리동)",
      "status": "영업/정상",
      "licenseDate": "2010-12-21"
    },
    {
      "name": "탑플러스마트",
      "address": "부산광역시 사하구 하단동 510-9 초이스타워",
      "roadAddress": "부산광역시 사하구 낙동대로 498  (하단동,초이스타워)",
      "status": "영업/정상",
      "licenseDate": "2010-12-20"
    },
    {
      "name": "GS25장림세정점",
      "address": "부산광역시 사하구 장림동 1052-1",
      "roadAddress": "부산광역시 사하구 을숙도대로 662  (장림동)",
      "status": "영업/정상",
      "licenseDate": "2010-12-23"
    },
    {
      "name": "신구멍가게",
      "address": "부산광역시 사하구 하단동 503-1",
      "roadAddress": "부산광역시 사하구 낙동대로519번길 75  (하단동)",
      "status": "영업/정상",
      "licenseDate": "2011-01-04"
    },
    {
      "name": "파워C마트",
      "address": "부산광역시 사하구 괴정동 487-24",
      "roadAddress": "부산광역시 사하구 괴정로 288  (괴정동)",
      "status": "영업/정상",
      "licenseDate": "2011-01-18"
    },
    {
      "name": "훼미리마트하단SK점",
      "address": "부산광역시 사하구 하단동 1157-20 세진빌딩 103호",
      "roadAddress": "부산광역시 사하구 하신번영로 423,  103호 (하단동,세진빌딩)",
      "status": "영업/정상",
      "licenseDate": "2011-01-20"
    },
    {
      "name": "GS25다대성원점",
      "address": "부산광역시 사하구 다대동 1551-25",
      "roadAddress": "부산광역시 사하구 다대로 636  (다대동)",
      "status": "영업/정상",
      "licenseDate": "2011-02-07"
    },
    {
      "name": "한일마트",
      "address": "부산광역시 사하구 감천동 13-993",
      "roadAddress": "부산광역시 사하구 옥천로 62-2  (감천동)",
      "status": "영업/정상",
      "licenseDate": "2011-02-09"
    },
    {
      "name": "포시즌동아대점",
      "address": "부산광역시 사하구 하단동 492-20",
      "roadAddress": "부산광역시 사하구 낙동대로516번길 39  (하단동)",
      "status": "영업/정상",
      "licenseDate": "2011-02-14"
    },
    {
      "name": "뉴코아아울렛괴정점",
      "address": "부산광역시 사하구 괴정동 961",
      "roadAddress": "",
      "status": "영업/정상",
      "licenseDate": "2011-02-18"
    },
    {
      "name": "훼미리마트 하단 나산점",
      "address": "부산광역시 사하구 하단동 870-95 나산리츠101호",
      "roadAddress": "부산광역시 사하구 낙동남로 1362  (하단동,나산리츠101호)",
      "status": "영업/정상",
      "licenseDate": "2011-02-21"
    },
    {
      "name": "GS25 괴정럭키점",
      "address": "부산광역시 사하구 괴정동 1102-7",
      "roadAddress": "부산광역시 사하구 마하로 10  (괴정동)",
      "status": "영업/정상",
      "licenseDate": "2011-02-22"
    },
    {
      "name": "벽산태양할인마트",
      "address": "부산광역시 사하구 당리동 66 벽산태양할인마트 상가동 101,102호",
      "roadAddress": "부산광역시 사하구 승학로71번길 60, 상가동 101,102호 (당리동,벽산태양할인마트)",
      "status": "영업/정상",
      "licenseDate": "2011-03-08"
    },
    {
      "name": "경동태양할인마트",
      "address": "부산광역시 사하구 장림동 2 장림경동윈츠그린아파트 102동 101호",
      "roadAddress": "부산광역시 사하구 다대로277번길 124, 102동 101호 (장림동,장림경동윈츠그린아파트)",
      "status": "영업/정상",
      "licenseDate": "2011-03-08"
    },
    {
      "name": "홈플러스(주)하단점",
      "address": "부산광역시 사하구 하단동 1184-1",
      "roadAddress": "부산광역시 사하구 하신번영로201번길 10  (하단동)",
      "status": "영업/정상",
      "licenseDate": "2011-03-08"
    },
    {
      "name": "홈플러스(주)다대포점",
      "address": "부산광역시 사하구 다대동 1548-18",
      "roadAddress": "부산광역시 사하구 다대낙조2길 3  (다대동)",
      "status": "영업/정상",
      "licenseDate": "2011-03-08"
    },
    {
      "name": "하프타임대박점",
      "address": "부산광역시 사하구 장림동 산 29-7",
      "roadAddress": "",
      "status": "영업/정상",
      "licenseDate": "2011-03-11"
    },
    {
      "name": "포시즌",
      "address": "부산광역시 사하구 괴정동 553-9",
      "roadAddress": "부산광역시 사하구 장평로 441  (괴정동)",
      "status": "영업/정상",
      "licenseDate": "2011-03-18"
    },
    {
      "name": "파워C마트",
      "address": "부산광역시 사하구 감천동 174-1",
      "roadAddress": "부산광역시 사하구 감천로 170  (감천동)",
      "status": "영업/정상",
      "licenseDate": "2011-03-22"
    },
    {
      "name": "영화세상",
      "address": "부산광역시 사하구 당리동 350-38",
      "roadAddress": "부산광역시 사하구 승학로 146-1  (당리동)",
      "status": "영업/정상",
      "licenseDate": "2011-03-30"
    },
    {
      "name": "다대빅마트",
      "address": "부산광역시 사하구 다대동 1138",
      "roadAddress": "부산광역시 사하구 다대로529번길 14  (다대동)",
      "status": "영업/정상",
      "licenseDate": "2011-04-05"
    },
    {
      "name": "강서할인마트",
      "address": "부산광역시 사하구 하단동 589-1",
      "roadAddress": "부산광역시 사하구 낙동남로 1406 (하단동)",
      "status": "영업/정상",
      "licenseDate": "2011-04-12"
    },
    {
      "name": "썬마트",
      "address": "부산광역시 사하구 감천동 715-1",
      "roadAddress": "",
      "status": "영업/정상",
      "licenseDate": "2011-04-14"
    },
    {
      "name": "구평상회",
      "address": "부산광역시 사하구 구평동 105-5",
      "roadAddress": "부산광역시 사하구 을숙도대로745번길 8  (구평동)",
      "status": "영업/정상",
      "licenseDate": "2011-04-18"
    },
    {
      "name": "세븐괴정4호점",
      "address": "부산광역시 사하구 괴정동 554-11",
      "roadAddress": "",
      "status": "영업/정상",
      "licenseDate": "2011-04-20"
    },
    {
      "name": "스펀지마트",
      "address": "부산광역시 사하구 다대동 151 153-1, 154 경동빌딩 1층",
      "roadAddress": "",
      "status": "영업/정상",
      "licenseDate": "2011-04-25"
    },
    {
      "name": "그린상회",
      "address": "부산광역시 사하구 장림동 615-94",
      "roadAddress": "부산광역시 사하구 장림시장9길 137  (장림동)",
      "status": "영업/정상",
      "licenseDate": "2011-05-04"
    },
    {
      "name": "천복마트",
      "address": "부산광역시 사하구 감천동 9-95",
      "roadAddress": "",
      "status": "영업/정상",
      "licenseDate": "2011-05-17"
    },
    {
      "name": "미니스톱하단에덴점",
      "address": "부산광역시 사하구 하단동 500-71",
      "roadAddress": "",
      "status": "영업/정상",
      "licenseDate": "2011-05-17"
    },
    {
      "name": "GS25승학점",
      "address": "부산광역시 사하구 하단동 800-9",
      "roadAddress": "부산광역시 사하구 낙동대로550번길 5  (하단동)",
      "status": "영업/정상",
      "licenseDate": "2011-05-20"
    },
    {
      "name": "두송할인마트",
      "address": "부산광역시 사하구 다대동 96 두송아파트 상가지하동 203호",
      "roadAddress": "부산광역시 사하구 다대로381번길 105, 상가지하동 203호 (다대동,두송아파트)",
      "status": "영업/정상",
      "licenseDate": "2011-05-23"
    },
    {
      "name": "에이스마트",
      "address": "부산광역시 사하구 다대동 948-1 조성상가 9동 1층호",
      "roadAddress": "",
      "status": "영업/정상",
      "licenseDate": "2011-05-26"
    },
    {
      "name": "현대할인마트",
      "address": "부산광역시 사하구 괴정동 342-3",
      "roadAddress": "부산광역시 사하구 낙동대로 106  (괴정동)",
      "status": "영업/정상",
      "licenseDate": "2011-06-02"
    },
    {
      "name": "훼미리마트구평점",
      "address": "부산광역시 사하구 구평동 125-16",
      "roadAddress": "부산광역시 사하구 을숙도대로 746  (구평동)",
      "status": "영업/정상",
      "licenseDate": "2011-06-02"
    },
    {
      "name": "아이앤지25(사하점)",
      "address": "부산광역시 사하구 당리동 341-13",
      "roadAddress": "",
      "status": "영업/정상",
      "licenseDate": "2011-06-09"
    },
    {
      "name": "빅세일마트",
      "address": "부산광역시 사하구 괴정동 733",
      "roadAddress": "부산광역시 사하구 낙동대로 265  (괴정동)",
      "status": "영업/정상",
      "licenseDate": "1998-06-12"
    }
  ]
}